{
  "aland_no": 226,
  "title": "Concerning the Law",
  "title_de": "Zum Gesetz",
  "description": "Evangelien-Querverweise: automatisch gruppierte Marker innerhalb dieser Perikope (nur Matthaeus, Markus, Lukas, Johannes). Dieselben Vers-Zuordnungen gelten fuer alle Lesetexte. Kurzlabels vom ersten Vers der Gruppe (Elberfelder 1905).",
  "source": "cross_references_chinese_whispers_v1",
  "translation_reference": "elberfelder_1905",
  "refs": {
    "matthew": "11.12-13 5.18",
    "mark": "",
    "luke": "16.16-17",
    "john": ""
  },
  "groups": [
    {
      "id": "crossref_01",
      "label": "Denn wahrlich, ich sage euch: Bis der Himmel und die Erde vergehen, soll auch nicht ein…",
      "marker": "apricot",
      "verses": [
        "40:5:18",
        "42:16:17"
      ]
    },
    {
      "id": "crossref_02",
      "label": "Aber von den Tagen Johannes' des Täufers an bis jetzt wird dem Reiche der Himmel Gewalt…",
      "marker": "blush",
      "verses": [
        "40:11:12",
        "42:16:16"
      ]
    }
  ]
}
